setup.py
brainfuckterpreter/__init__.py
brainfuckterpreter/bf.py
brainfuckterpreter.egg-info/PKG-INFO
brainfuckterpreter.egg-info/SOURCES.txt
brainfuckterpreter.egg-info/dependency_links.txt
brainfuckterpreter.egg-info/top_level.txt