Metadata-Version: 1.0
Name: brainfuckterpreter
Version: 0.1
Summary: An interpreter for brainfuck
Home-page: https://github.com/caseybrichardson/brainfuckterpreter
Author: Casey Richardson
Author-email: caseybrichardson@icloud.com
License: MIT
Platform: UNKNOWN
